warpdatasets/__init__.py
warpdatasets/compat.py
warpdatasets/addons/__init__.py
warpdatasets/addons/builder.py
warpdatasets/addons/embedding_space.py
warpdatasets/addons/publish.py
warpdatasets/api/__init__.py
warpdatasets/api/dataset.py
warpdatasets/artifacts/__init__.py
warpdatasets/artifacts/index.py
warpdatasets/artifacts/resolver.py
warpdatasets/artifacts/tar/__init__.py
warpdatasets/artifacts/tar/index_builder.py
warpdatasets/artifacts/tar/reader.py
warpdatasets/cache/__init__.py
warpdatasets/cache/blob_cache.py
warpdatasets/cache/context.py
warpdatasets/catalog/__init__.py
warpdatasets/catalog/cache.py
warpdatasets/catalog/resolver.py
warpdatasets/catalog/store.py
warpdatasets/catalog/stores/__init__.py
warpdatasets/catalog/stores/chain.py
warpdatasets/catalog/stores/file.py
warpdatasets/catalog/stores/http.py
warpdatasets/catalog/stores/s3.py
warpdatasets/cli/__init__.py
warpdatasets/cli/main.py
warpdatasets/cli/commands/__init__.py
warpdatasets/cli/commands/cache.py
warpdatasets/cli/commands/cat.py
warpdatasets/cli/commands/doctor.py
warpdatasets/cli/commands/embeddings.py
warpdatasets/cli/commands/head.py
warpdatasets/cli/commands/info.py
warpdatasets/cli/commands/ingest.py
warpdatasets/cli/commands/init.py
warpdatasets/cli/commands/inspect.py
warpdatasets/cli/commands/ls.py
warpdatasets/cli/commands/publish.py
warpdatasets/cli/commands/register.py
warpdatasets/cli/commands/schema.py
warpdatasets/cli/commands/stream.py
warpdatasets/cli/commands/sync.py
warpdatasets/cli/commands/warm.py
warpdatasets/config/__init__.py
warpdatasets/config/settings.py
warpdatasets/engines/__init__.py
warpdatasets/engines/duckdb.py
warpdatasets/ingest/__init__.py
warpdatasets/ingest/base.py
warpdatasets/ingest/csv_files.py
warpdatasets/ingest/imagefolder.py
warpdatasets/ingest/paired.py
warpdatasets/manifest/__init__.py
warpdatasets/manifest/canon.py
warpdatasets/manifest/model.py
warpdatasets/manifest/validate.py
warpdatasets/prefetch/__init__.py
warpdatasets-3.0.14.dist-info/METADATA
warpdatasets-3.0.14.dist-info/WHEEL
warpdatasets-3.0.14.dist-info/entry_points.txt
warpdatasets-3.0.14.dist-info/RECORD
